{"AMZN":{"as-of":"2020-05-29","previous":"2442.3700","weight":"0.00","effectiveDate":null,"fetchedDate":null,"sectorDescription":null,"1wk":-0.179,"2wk":2.24,"4wk":-1.278,"8wk":28.027,"1qtr":23.378,"1yr":30.678,"YTD":32.174,"priceGain":{"1wk":{"startDate":"2020-05-21","endDate":"2020-05-29","last":"2442.3700","prevClose":"2446.7400","gain":-0.179},"2wk":{"startDate":"2020-05-14","endDate":"2020-05-29","last":"2442.3700","prevClose":"2388.8500","gain":2.24},"4wk":{"startDate":"2020-04-30","endDate":"2020-05-29","last":"2442.3700","prevClose":"2474.0000","gain":-1.278},"8wk":{"startDate":"2020-04-01","endDate":"2020-05-29","last":"2442.3700","prevClose":"1907.7000","gain":28.027},"1qtr":{"startDate":"2020-02-26","endDate":"2020-05-29","last":"2442.3700","prevClose":"1979.5900","gain":23.378},"1yr":{"startDate":"2019-05-17","endDate":"2020-05-29","last":"2442.3700","prevClose":"1869.0000","gain":30.678},"YTD":{"startDate":"2019-12-31","endDate":"2020-05-29","last":"2442.3700","prevClose":"1847.8400","gain":32.174}},"basis":1863.665,"shares":16},"BIP":{"as-of":"2020-05-29","previous":"40.6600","weight":"0.00","effectiveDate":null,"fetchedDate":null,"sectorDescription":null,"1wk":4.016,"2wk":4.524,"4wk":3.751,"8wk":18.232,"1qtr":-24.227,"1yr":-3.006,"YTD":-18.664,"priceGain":{"1wk":{"startDate":"2020-05-21","endDate":"2020-05-29","last":"40.6600","prevClose":"39.0900","gain":4.016},"2wk":{"startDate":"2020-05-14","endDate":"2020-05-29","last":"40.6600","prevClose":"38.9000","gain":4.524},"4wk":{"startDate":"2020-04-30","endDate":"2020-05-29","last":"40.6600","prevClose":"39.1900","gain":3.751},"8wk":{"startDate":"2020-04-01","endDate":"2020-05-29","last":"40.6600","prevClose":"34.3900","gain":18.232},"1qtr":{"startDate":"2020-02-26","endDate":"2020-05-29","last":"40.6600","prevClose":"53.6600","gain":-24.227},"1yr":{"startDate":"2019-05-17","endDate":"2020-05-29","last":"40.6600","prevClose":"41.9200","gain":-3.006},"YTD":{"startDate":"2019-12-31","endDate":"2020-05-29","last":"40.6600","prevClose":"49.9900","gain":-18.664}},"basis":40.44,"shares":"111"},"BRK.B":{"as-of":"2020-05-29","previous":"185.5800","weight":"0.00","effectiveDate":null,"fetchedDate":null,"sectorDescription":null,"1wk":6.082,"2wk":8.571,"4wk":-0.95,"8wk":5.473,"1qtr":-14.107,"1yr":-8.703,"YTD":-18.066,"priceGain":{"1wk":{"startDate":"2020-05-21","endDate":"2020-05-29","last":"185.5800","prevClose":"174.9400","gain":6.082},"2wk":{"startDate":"2020-05-14","endDate":"2020-05-29","last":"185.5800","prevClose":"170.9300","gain":8.571},"4wk":{"startDate":"2020-04-30","endDate":"2020-05-29","last":"185.5800","prevClose":"187.3600","gain":-0.95},"8wk":{"startDate":"2020-04-01","endDate":"2020-05-29","last":"185.5800","prevClose":"175.9500","gain":5.473},"1qtr":{"startDate":"2020-02-26","endDate":"2020-05-29","last":"185.5800","prevClose":"216.0600","gain":-14.107},"1yr":{"startDate":"2019-05-17","endDate":"2020-05-29","last":"185.5800","prevClose":"203.2700","gain":-8.703},"YTD":{"startDate":"2019-12-31","endDate":"2020-05-29","last":"185.5800","prevClose":"226.5000","gain":-18.066}},"basis":178.082,"shares":76},"DAM":{"as-of":"2020-05-29","previous":"14.973213","weight":"0.00","effectiveDate":"2020-01-10","fetchedDate":"2020-01-10","sectorDescription":"Damwidi","1wk":1.872,"2wk":4.849,"4wk":3.927,"8wk":25.9,"1qtr":5.135,"1yr":9.172,"YTD":6.162,"priceGain":{"1wk":{"startDate":"2020-05-21","endDate":"2020-05-29","last":"14.973213","prevClose":"14.698029","gain":1.872},"2wk":{"startDate":"2020-05-14","endDate":"2020-05-29","last":"14.973213","prevClose":"14.280781","gain":4.849},"4wk":{"startDate":"2020-04-30","endDate":"2020-05-29","last":"14.973213","prevClose":"14.407459","gain":3.927},"8wk":{"startDate":"2020-04-01","endDate":"2020-05-29","last":"14.973213","prevClose":"11.892902","gain":25.9},"1qtr":{"startDate":"2020-02-26","endDate":"2020-05-29","last":"14.973213","prevClose":"14.241909","gain":5.135},"1yr":{"startDate":"2019-05-17","endDate":"2020-05-29","last":"14.973213","prevClose":"13.715188","gain":9.172},"YTD":{"startDate":"2019-12-31","endDate":"2020-05-29","last":"14.973213","prevClose":"14.104133","gain":6.162}},"basis":0,"shares":0},"IGV":{"as-of":"2020-05-29","previous":"267.2700","weight":"0.00","effectiveDate":null,"fetchedDate":null,"sectorDescription":null,"1wk":3.625,"2wk":7.688,"4wk":10.956,"8wk":33.428,"1qtr":9.609,"1yr":23.828,"YTD":14.688,"priceGain":{"1wk":{"startDate":"2020-05-21","endDate":"2020-05-29","last":"267.2700","prevClose":"257.9200","gain":3.625},"2wk":{"startDate":"2020-05-14","endDate":"2020-05-29","last":"267.2700","prevClose":"248.1900","gain":7.688},"4wk":{"startDate":"2020-04-30","endDate":"2020-05-29","last":"267.2700","prevClose":"240.8800","gain":10.956},"8wk":{"startDate":"2020-04-01","endDate":"2020-05-29","last":"267.2700","prevClose":"200.3100","gain":33.428},"1qtr":{"startDate":"2020-02-26","endDate":"2020-05-29","last":"267.2700","prevClose":"243.8400","gain":9.609},"1yr":{"startDate":"2019-05-17","endDate":"2020-05-29","last":"267.2700","prevClose":"215.8400","gain":23.828},"YTD":{"startDate":"2019-12-31","endDate":"2020-05-29","last":"267.2700","prevClose":"233.0400","gain":14.688}},"basis":251.899,"shares":"80"},"SPY":{"as-of":"2020-05-29","previous":"304.3200","weight":"0.00","effectiveDate":"2020-01-10","fetchedDate":"2020-01-10","sectorDescription":"S&P 500","1wk":3.201,"2wk":6.79,"4wk":4.765,"8wk":23.632,"1qtr":-2.305,"1yr":6.465,"YTD":-5.45,"priceGain":{"1wk":{"startDate":"2020-05-21","endDate":"2020-05-29","last":"304.3200","prevClose":"294.8800","gain":3.201},"2wk":{"startDate":"2020-05-14","endDate":"2020-05-29","last":"304.3200","prevClose":"284.9700","gain":6.79},"4wk":{"startDate":"2020-04-30","endDate":"2020-05-29","last":"304.3200","prevClose":"290.4800","gain":4.765},"8wk":{"startDate":"2020-04-01","endDate":"2020-05-29","last":"304.3200","prevClose":"246.1500","gain":23.632},"1qtr":{"startDate":"2020-02-26","endDate":"2020-05-29","last":"304.3200","prevClose":"311.5000","gain":-2.305},"1yr":{"startDate":"2019-05-17","endDate":"2020-05-29","last":"304.3200","prevClose":"285.8400","gain":6.465},"YTD":{"startDate":"2019-12-31","endDate":"2020-05-29","last":"304.3200","prevClose":"321.8600","gain":-5.45}},"basis":336.461,"shares":134},"XLB":{"as-of":"2020-05-29","previous":"55.4500","weight":"2.40","effectiveDate":"2020-04-07","fetchedDate":"2020-04-07","sectorDescription":"Materials","1wk":4.603,"2wk":9.954,"4wk":6.881,"8wk":28.924,"1qtr":-0.84,"1yr":1.464,"YTD":-9.72,"priceGain":{"1wk":{"startDate":"2020-05-21","endDate":"2020-05-29","last":"55.4500","prevClose":"53.0100","gain":4.603},"2wk":{"startDate":"2020-05-14","endDate":"2020-05-29","last":"55.4500","prevClose":"50.4300","gain":9.954},"4wk":{"startDate":"2020-04-30","endDate":"2020-05-29","last":"55.4500","prevClose":"51.8800","gain":6.881},"8wk":{"startDate":"2020-04-01","endDate":"2020-05-29","last":"55.4500","prevClose":"43.0100","gain":28.924},"1qtr":{"startDate":"2020-02-26","endDate":"2020-05-29","last":"55.4500","prevClose":"55.9200","gain":-0.84},"1yr":{"startDate":"2019-05-17","endDate":"2020-05-29","last":"55.4500","prevClose":"54.6500","gain":1.464},"YTD":{"startDate":"2019-12-31","endDate":"2020-05-29","last":"55.4500","prevClose":"61.4200","gain":-9.72}},"basis":0,"shares":0},"XLC":{"as-of":"2020-05-29","previous":"54.0200","weight":"10.70","effectiveDate":"2020-04-07","fetchedDate":"2020-04-07","sectorDescription":"Communication Services","1wk":1.18,"2wk":6.864,"4wk":7.438,"8wk":27.166,"1qtr":2.524,"1yr":10.245,"YTD":0.727,"priceGain":{"1wk":{"startDate":"2020-05-21","endDate":"2020-05-29","last":"54.0200","prevClose":"53.3900","gain":1.18},"2wk":{"startDate":"2020-05-14","endDate":"2020-05-29","last":"54.0200","prevClose":"50.5500","gain":6.864},"4wk":{"startDate":"2020-04-30","endDate":"2020-05-29","last":"54.0200","prevClose":"50.2800","gain":7.438},"8wk":{"startDate":"2020-04-01","endDate":"2020-05-29","last":"54.0200","prevClose":"42.4800","gain":27.166},"1qtr":{"startDate":"2020-02-26","endDate":"2020-05-29","last":"54.0200","prevClose":"52.6900","gain":2.524},"1yr":{"startDate":"2019-05-17","endDate":"2020-05-29","last":"54.0200","prevClose":"49.0000","gain":10.245},"YTD":{"startDate":"2019-12-31","endDate":"2020-05-29","last":"54.0200","prevClose":"53.6300","gain":0.727}},"basis":0,"shares":0},"XLE":{"as-of":"2020-05-29","previous":"38.7600","weight":"2.60","effectiveDate":"2020-04-07","fetchedDate":"2020-04-07","sectorDescription":"Energy","1wk":0.103,"2wk":7.279,"4wk":2,"8wk":40.333,"1qtr":-19.031,"1yr":-39.2,"YTD":-35.443,"priceGain":{"1wk":{"startDate":"2020-05-21","endDate":"2020-05-29","last":"38.7600","prevClose":"38.7200","gain":0.103},"2wk":{"startDate":"2020-05-14","endDate":"2020-05-29","last":"38.7600","prevClose":"36.1300","gain":7.279},"4wk":{"startDate":"2020-04-30","endDate":"2020-05-29","last":"38.7600","prevClose":"38.0000","gain":2},"8wk":{"startDate":"2020-04-01","endDate":"2020-05-29","last":"38.7600","prevClose":"27.6200","gain":40.333},"1qtr":{"startDate":"2020-02-26","endDate":"2020-05-29","last":"38.7600","prevClose":"47.8700","gain":-19.031},"1yr":{"startDate":"2019-05-17","endDate":"2020-05-29","last":"38.7600","prevClose":"63.7500","gain":-39.2},"YTD":{"startDate":"2019-12-31","endDate":"2020-05-29","last":"38.7600","prevClose":"60.0400","gain":-35.443}},"basis":0,"shares":0},"XLF":{"as-of":"2020-05-29","previous":"23.4100","weight":"10.90","effectiveDate":"2020-04-07","fetchedDate":"2020-04-07","sectorDescription":"Financials","1wk":6.409,"2wk":10.477,"4wk":2.72,"8wk":19.744,"1qtr":-18.004,"1yr":-12.909,"YTD":-23.944,"priceGain":{"1wk":{"startDate":"2020-05-21","endDate":"2020-05-29","last":"23.4100","prevClose":"22.0000","gain":6.409},"2wk":{"startDate":"2020-05-14","endDate":"2020-05-29","last":"23.4100","prevClose":"21.1900","gain":10.477},"4wk":{"startDate":"2020-04-30","endDate":"2020-05-29","last":"23.4100","prevClose":"22.7900","gain":2.72},"8wk":{"startDate":"2020-04-01","endDate":"2020-05-29","last":"23.4100","prevClose":"19.5500","gain":19.744},"1qtr":{"startDate":"2020-02-26","endDate":"2020-05-29","last":"23.4100","prevClose":"28.5500","gain":-18.004},"1yr":{"startDate":"2019-05-17","endDate":"2020-05-29","last":"23.4100","prevClose":"26.8800","gain":-12.909},"YTD":{"startDate":"2019-12-31","endDate":"2020-05-29","last":"23.4100","prevClose":"30.7800","gain":-23.944}},"basis":0,"shares":0},"XLI":{"as-of":"2020-05-29","previous":"67.6700","weight":"8.20","effectiveDate":"2020-04-07","fetchedDate":"2020-04-07","sectorDescription":"Industrials","1wk":5.916,"2wk":13.407,"4wk":5.389,"8wk":20.089,"1qtr":-12.469,"1yr":-9.556,"YTD":-16.939,"priceGain":{"1wk":{"startDate":"2020-05-21","endDate":"2020-05-29","last":"67.6700","prevClose":"63.8900","gain":5.916},"2wk":{"startDate":"2020-05-14","endDate":"2020-05-29","last":"67.6700","prevClose":"59.6700","gain":13.407},"4wk":{"startDate":"2020-04-30","endDate":"2020-05-29","last":"67.6700","prevClose":"64.2100","gain":5.389},"8wk":{"startDate":"2020-04-01","endDate":"2020-05-29","last":"67.6700","prevClose":"56.3500","gain":20.089},"1qtr":{"startDate":"2020-02-26","endDate":"2020-05-29","last":"67.6700","prevClose":"77.3100","gain":-12.469},"1yr":{"startDate":"2019-05-17","endDate":"2020-05-29","last":"67.6700","prevClose":"74.8200","gain":-9.556},"YTD":{"startDate":"2019-12-31","endDate":"2020-05-29","last":"67.6700","prevClose":"81.4700","gain":-16.939}},"basis":0,"shares":0},"XLK":{"as-of":"2020-05-29","previous":"97.9700","weight":"25.50","effectiveDate":"2020-04-07","fetchedDate":"2020-04-07","sectorDescription":"Information Technology","1wk":1.903,"2wk":5.344,"4wk":7.176,"8wk":27.998,"1qtr":5.685,"1yr":29.968,"YTD":6.872,"priceGain":{"1wk":{"startDate":"2020-05-21","endDate":"2020-05-29","last":"97.9700","prevClose":"96.1400","gain":1.903},"2wk":{"startDate":"2020-05-14","endDate":"2020-05-29","last":"97.9700","prevClose":"93.0000","gain":5.344},"4wk":{"startDate":"2020-04-30","endDate":"2020-05-29","last":"97.9700","prevClose":"91.4100","gain":7.176},"8wk":{"startDate":"2020-04-01","endDate":"2020-05-29","last":"97.9700","prevClose":"76.5400","gain":27.998},"1qtr":{"startDate":"2020-02-26","endDate":"2020-05-29","last":"97.9700","prevClose":"92.7000","gain":5.685},"1yr":{"startDate":"2019-05-17","endDate":"2020-05-29","last":"97.9700","prevClose":"75.3800","gain":29.968},"YTD":{"startDate":"2019-12-31","endDate":"2020-05-29","last":"97.9700","prevClose":"91.6700","gain":6.872}},"basis":77.101,"shares":524},"XLP":{"as-of":"2020-05-29","previous":"59.2300","weight":"7.80","effectiveDate":"2020-04-07","fetchedDate":"2020-04-07","sectorDescription":"Consumer Staples","1wk":3.422,"2wk":4.113,"4wk":1.665,"8wk":10.607,"1qtr":-3.957,"1yr":2.563,"YTD":-5.954,"priceGain":{"1wk":{"startDate":"2020-05-21","endDate":"2020-05-29","last":"59.2300","prevClose":"57.2700","gain":3.422},"2wk":{"startDate":"2020-05-14","endDate":"2020-05-29","last":"59.2300","prevClose":"56.8900","gain":4.113},"4wk":{"startDate":"2020-04-30","endDate":"2020-05-29","last":"59.2300","prevClose":"58.2600","gain":1.665},"8wk":{"startDate":"2020-04-01","endDate":"2020-05-29","last":"59.2300","prevClose":"53.5500","gain":10.607},"1qtr":{"startDate":"2020-02-26","endDate":"2020-05-29","last":"59.2300","prevClose":"61.6700","gain":-3.957},"1yr":{"startDate":"2019-05-17","endDate":"2020-05-29","last":"59.2300","prevClose":"57.7500","gain":2.563},"YTD":{"startDate":"2019-12-31","endDate":"2020-05-29","last":"59.2300","prevClose":"62.9800","gain":-5.954}},"basis":0,"shares":0},"XLRE":{"as-of":"2020-05-29","previous":"34.6500","weight":"3.00","effectiveDate":"2020-04-07","fetchedDate":"2020-04-07","sectorDescription":"","1wk":8.281,"2wk":11.451,"4wk":2.152,"8wk":18.99,"1qtr":-13.332,"1yr":-5.431,"YTD":-10.396,"priceGain":{"1wk":{"startDate":"2020-05-21","endDate":"2020-05-29","last":"34.6500","prevClose":"32.0000","gain":8.281},"2wk":{"startDate":"2020-05-14","endDate":"2020-05-29","last":"34.6500","prevClose":"31.0900","gain":11.451},"4wk":{"startDate":"2020-04-30","endDate":"2020-05-29","last":"34.6500","prevClose":"33.9200","gain":2.152},"8wk":{"startDate":"2020-04-01","endDate":"2020-05-29","last":"34.6500","prevClose":"29.1200","gain":18.99},"1qtr":{"startDate":"2020-02-26","endDate":"2020-05-29","last":"34.6500","prevClose":"39.9800","gain":-13.332},"1yr":{"startDate":"2019-05-17","endDate":"2020-05-29","last":"34.6500","prevClose":"36.6400","gain":-5.431},"YTD":{"startDate":"2019-12-31","endDate":"2020-05-29","last":"34.6500","prevClose":"38.6700","gain":-10.396}},"basis":0,"shares":0},"XLU":{"as-of":"2020-05-29","previous":"59.6900","weight":"3.60","effectiveDate":"2020-04-07","fetchedDate":"2020-04-07","sectorDescription":"Utilities","1wk":6.856,"2wk":7.453,"4wk":4.244,"8wk":14.612,"1qtr":-11.387,"1yr":1.548,"YTD":-7.629,"priceGain":{"1wk":{"startDate":"2020-05-21","endDate":"2020-05-29","last":"59.6900","prevClose":"55.8600","gain":6.856},"2wk":{"startDate":"2020-05-14","endDate":"2020-05-29","last":"59.6900","prevClose":"55.5500","gain":7.453},"4wk":{"startDate":"2020-04-30","endDate":"2020-05-29","last":"59.6900","prevClose":"57.2600","gain":4.244},"8wk":{"startDate":"2020-04-01","endDate":"2020-05-29","last":"59.6900","prevClose":"52.0800","gain":14.612},"1qtr":{"startDate":"2020-02-26","endDate":"2020-05-29","last":"59.6900","prevClose":"67.3600","gain":-11.387},"1yr":{"startDate":"2019-05-17","endDate":"2020-05-29","last":"59.6900","prevClose":"58.7800","gain":1.548},"YTD":{"startDate":"2019-12-31","endDate":"2020-05-29","last":"59.6900","prevClose":"64.6200","gain":-7.629}},"basis":0,"shares":0},"XLV":{"as-of":"2020-05-29","previous":"103.0100","weight":"15.40","effectiveDate":"2020-04-07","fetchedDate":"2020-04-07","sectorDescription":"Health Care","1wk":3.621,"2wk":3.444,"4wk":3.289,"8wk":20.89,"1qtr":6.065,"1yr":16.474,"YTD":1.129,"priceGain":{"1wk":{"startDate":"2020-05-21","endDate":"2020-05-29","last":"103.0100","prevClose":"99.4100","gain":3.621},"2wk":{"startDate":"2020-05-14","endDate":"2020-05-29","last":"103.0100","prevClose":"99.5800","gain":3.444},"4wk":{"startDate":"2020-04-30","endDate":"2020-05-29","last":"103.0100","prevClose":"99.7300","gain":3.289},"8wk":{"startDate":"2020-04-01","endDate":"2020-05-29","last":"103.0100","prevClose":"85.2100","gain":20.89},"1qtr":{"startDate":"2020-02-26","endDate":"2020-05-29","last":"103.0100","prevClose":"97.1200","gain":6.065},"1yr":{"startDate":"2019-05-17","endDate":"2020-05-29","last":"103.0100","prevClose":"88.4400","gain":16.474},"YTD":{"startDate":"2019-12-31","endDate":"2020-05-29","last":"103.0100","prevClose":"101.8600","gain":1.129}},"basis":0,"shares":0},"XLY":{"as-of":"2020-05-29","previous":"124.1900","weight":"9.80","effectiveDate":"2020-04-07","fetchedDate":"2020-04-07","sectorDescription":"Consumer Discretionary","1wk":2.29,"2wk":8.795,"4wk":6.509,"8wk":32.54,"1qtr":2.222,"1yr":7.143,"YTD":-0.981,"priceGain":{"1wk":{"startDate":"2020-05-21","endDate":"2020-05-29","last":"124.1900","prevClose":"121.4100","gain":2.29},"2wk":{"startDate":"2020-05-14","endDate":"2020-05-29","last":"124.1900","prevClose":"114.1500","gain":8.795},"4wk":{"startDate":"2020-04-30","endDate":"2020-05-29","last":"124.1900","prevClose":"116.6000","gain":6.509},"8wk":{"startDate":"2020-04-01","endDate":"2020-05-29","last":"124.1900","prevClose":"93.7000","gain":32.54},"1qtr":{"startDate":"2020-02-26","endDate":"2020-05-29","last":"124.1900","prevClose":"121.4900","gain":2.222},"1yr":{"startDate":"2019-05-17","endDate":"2020-05-29","last":"124.1900","prevClose":"115.9100","gain":7.143},"YTD":{"startDate":"2019-12-31","endDate":"2020-05-29","last":"124.1900","prevClose":"125.4200","gain":-0.981}},"basis":0,"shares":0}}